ssmenv/__init__.py
ssmenv-2.1.0.dist-info/LICENSE
ssmenv-2.1.0.dist-info/WHEEL
ssmenv-2.1.0.dist-info/METADATA
ssmenv-2.1.0.dist-info/RECORD
